id_recognizer/__init__.py
id_recognizer/composition_id_recognizer.py
id_recognizer/dep.txt
id_recognizer/recognizer_test.py
id_recognizer-1.0.3.dist-info/METADATA
id_recognizer-1.0.3.dist-info/WHEEL
id_recognizer-1.0.3.dist-info/licenses/LICENSE
id_recognizer-1.0.3.dist-info/RECORD
